cpsplines/__init__.py
cpsplines/fittings/__init__.py
cpsplines/fittings/fit_cpsplines.py
cpsplines/graphics/__init__.py
cpsplines/graphics/plot_curves.py
cpsplines/graphics/plot_surfaces.py
cpsplines/mosek_functions/__init__.py
cpsplines/mosek_functions/interval_constraints.py
cpsplines/mosek_functions/obj_function.py
cpsplines/mosek_functions/pdf_constraints.py
cpsplines/mosek_functions/point_constraints.py
cpsplines/psplines/__init__.py
cpsplines/psplines/bspline_basis.py
cpsplines/psplines/penalty_matrix.py
cpsplines/utils/__init__.py
cpsplines/utils/box_product.py
cpsplines/utils/cholesky_semidefinite.py
cpsplines/utils/clean_data_covid.py
cpsplines/utils/fast_kron.py
cpsplines/utils/gcv.py
cpsplines/utils/irls.py
cpsplines/utils/normalize_data.py
cpsplines/utils/rearrange_data.py
cpsplines/utils/simulator_grid_search.py
cpsplines/utils/simulator_optimize.py
cpsplines/utils/timer.py
cpsplines/utils/weighted_b.py
cpsplines-0.3.0.dist-info/LICENSE.md
cpsplines-0.3.0.dist-info/METADATA
cpsplines-0.3.0.dist-info/WHEEL
cpsplines-0.3.0.dist-info/top_level.txt
cpsplines-0.3.0.dist-info/RECORD
