Metadata-Version: 2.1
Name: cpsplines
Version: 0.3.0
Summary: Constrained P-splines
Home-page: https://github.com/ManuelNavarroGarcia/cpsplines/
Download-URL: https://github.com/ManuelNavarroGarcia/cpsplines/archive/refs/tags/0.3.0.tar.gz
Author: Manuel Navarro García
Author-email: manuelnavarrogithub@gmail.com
License: MIT
Keywords: P-splines,MOSEK,Python 3.12,Constraints,Optimization
Classifier: Development Status :: 3 - Alpha
Classifier: Topic :: Scientific/Engineering :: Mathematics
Classifier: License :: OSI Approved :: MIT License
Classifier: Programming Language :: Python :: 3
Classifier: Programming Language :: Python :: 3.12
Requires-Python: >=3.12
License-File: LICENSE.md
Requires-Dist: joblib
Requires-Dist: matplotlib
Requires-Dist: mosek
Requires-Dist: numpy
Requires-Dist: pandas
Requires-Dist: scipy
Requires-Dist: statsmodels
Requires-Dist: tensorly
Provides-Extra: dev
Requires-Dist: black[jupyter]; extra == "dev"
Requires-Dist: ipykernel; extra == "dev"
Requires-Dist: mypy; extra == "dev"
Requires-Dist: pip-tools>=7.0.0; extra == "dev"
Requires-Dist: pytest; extra == "dev"
Requires-Dist: ruff; extra == "dev"
